plex_posters/.DS_Store
plex_posters/__dev/__init__.py
plex_posters/__header__.py
plex_posters/__init__.py
plex_posters/__version__.py
plex_posters/config/__init__.py
plex_posters/config/config.py
plex_posters/library/__init__.py
plex_posters/test/test.py
plex_posters-0.1.4.dist-info/LICENSE
plex_posters-0.1.4.dist-info/WHEEL
plex_posters-0.1.4.dist-info/METADATA
plex_posters-0.1.4.dist-info/RECORD
