Metadata-Version: 2.1
Name: plex-posters
Version: 0.1.4
Summary: 
Author: dtomlinson
Author-email: dtomlinson@panaetius.co.uk
Requires-Python: >=3.8,<4.0
Classifier: Programming Language :: Python :: 3
Requires-Dist: praw (>=6.4,<7.0)
Requires-Dist: toml (>=0.10.0,<0.11.0)
